syneto_api/__init__.py
syneto_api/api_client.py
syneto_api/auth_api.py
syneto_api/central_api.py
syneto_api/jobs_api.py
syneto_api/keyring.py
syneto_api/node_api.py
syneto_api/protection_api.py
syneto_api/settings.py
syneto_api/storage_api.py
syneto_api/virt_api.py
syneto_api-0.3.62.dist-info/METADATA
syneto_api-0.3.62.dist-info/WHEEL
syneto_api-0.3.62.dist-info/RECORD
