Metadata-Version: 2.4
Name: syneto_api
Version: 0.3.62
Summary: Syneto Client API library
License: Proprietary
Author: Syneto
Author-email: developers@syneto.eu
Requires-Python: >=3.8,<4.0
Classifier: License :: Other/Proprietary License
Classifier: Programming Language :: Python :: 3
Classifier: Programming Language :: Python :: 3.8
Classifier: Programming Language :: Python :: 3.9
Classifier: Programming Language :: Python :: 3.10
Classifier: Programming Language :: Python :: 3.11
Classifier: Programming Language :: Python :: 3.12
Classifier: Programming Language :: Python :: 3.13
Classifier: Programming Language :: Python :: 3.14
Requires-Dist: aiodns (>=3,<4)
Requires-Dist: aiohttp (>=3.8,<4.0)
Requires-Dist: inflection (>=0.5,<0.6)
Requires-Dist: python-dotenv (>=0.16,<0.17)
Requires-Dist: requests[secure] (>=2.25,<3.0)
Requires-Dist: tenacity (>=8.0.1,<9.0.0,!=8.4.0)
Requires-Dist: typing_extensions (>=4.12,<5.0)
Project-URL: Homepage, https://github.com/SynetoNet/syneto-api
Project-URL: Repository, https://github.com/SynetoNet/syneto-api
